Metadata-Version: 2.4
Name: sisana
Version: 1.5.3
Summary: A command line interface tool to reconstruct and analyze single sample networks.
Author-email: Nolan Newman <nolan.newman@ncmm.uio.no>
License-Expression: MIT
Project-URL: Repository, https://github.com/kuijjerlab/sisana/
Keywords: transcription-factors,gene-regulatory-network,panda,lioness
Classifier: Development Status :: 5 - Production/Stable
Classifier: Programming Language :: Python :: 3
Classifier: Topic :: Scientific/Engineering :: Bio-Informatics
Requires-Python: >=3.9.0
License-File: LICENSE
Requires-Dist: numpy
Requires-Dist: pandas
Requires-Dist: netZooPy
Requires-Dist: scikit-learn
Requires-Dist: scikit-survival
Requires-Dist: matplotlib
Requires-Dist: pathlib
Requires-Dist: gseapy
Requires-Dist: seaborn
Requires-Dist: adjustText
Requires-Dist: pyyaml
Requires-Dist: pingouin
Requires-Dist: statannotations
Requires-Dist: requests
Requires-Dist: tqdm
Dynamic: license-file
